djangocms_teaser/__init__.py
djangocms_teaser/cms_plugins.py
djangocms_teaser/models.py
djangocms_teaser/locale/af/LC_MESSAGES/django.mo
djangocms_teaser/locale/af/LC_MESSAGES/django.po
djangocms_teaser/locale/ar/LC_MESSAGES/django.mo
djangocms_teaser/locale/ar/LC_MESSAGES/django.po
djangocms_teaser/locale/be/LC_MESSAGES/django.mo
djangocms_teaser/locale/be/LC_MESSAGES/django.po
djangocms_teaser/locale/bg/LC_MESSAGES/django.mo
djangocms_teaser/locale/bg/LC_MESSAGES/django.po
djangocms_teaser/locale/bn/LC_MESSAGES/django.mo
djangocms_teaser/locale/bn/LC_MESSAGES/django.po
djangocms_teaser/locale/ca/LC_MESSAGES/django.mo
djangocms_teaser/locale/ca/LC_MESSAGES/django.po
djangocms_teaser/locale/cmn/LC_MESSAGES/django.mo
djangocms_teaser/locale/cmn/LC_MESSAGES/django.po
djangocms_teaser/locale/cs/LC_MESSAGES/django.mo
djangocms_teaser/locale/cs/LC_MESSAGES/django.po
djangocms_teaser/locale/cy/LC_MESSAGES/django.mo
djangocms_teaser/locale/cy/LC_MESSAGES/django.po
djangocms_teaser/locale/da/LC_MESSAGES/django.mo
djangocms_teaser/locale/da/LC_MESSAGES/django.po
djangocms_teaser/locale/de/LC_MESSAGES/django.mo
djangocms_teaser/locale/de/LC_MESSAGES/django.po
djangocms_teaser/locale/el/LC_MESSAGES/django.mo
djangocms_teaser/locale/el/LC_MESSAGES/django.po
djangocms_teaser/locale/en/LC_MESSAGES/django.mo
djangocms_teaser/locale/en/LC_MESSAGES/django.po
djangocms_teaser/locale/es/LC_MESSAGES/django.mo
djangocms_teaser/locale/es/LC_MESSAGES/django.po
djangocms_teaser/locale/es_AR/LC_MESSAGES/django.mo
djangocms_teaser/locale/es_AR/LC_MESSAGES/django.po
djangocms_teaser/locale/es_BO/LC_MESSAGES/django.mo
djangocms_teaser/locale/es_BO/LC_MESSAGES/django.po
djangocms_teaser/locale/es_DO/LC_MESSAGES/django.mo
djangocms_teaser/locale/es_DO/LC_MESSAGES/django.po
djangocms_teaser/locale/et/LC_MESSAGES/django.mo
djangocms_teaser/locale/et/LC_MESSAGES/django.po
djangocms_teaser/locale/eu/LC_MESSAGES/django.mo
djangocms_teaser-0.2.0.dist-info/DESCRIPTION.rst
djangocms_teaser-0.2.0.dist-info/METADATA
djangocms_teaser-0.2.0.dist-info/metadata.json
djangocms_teaser-0.2.0.dist-info/RECORD
djangocms_teaser-0.2.0.dist-info/top_level.txt
djangocms_teaser-0.2.0.dist-info/WHEEL
